README
consistenthashing.py
setup.py
ConsistentHashing.egg-info/PKG-INFO
ConsistentHashing.egg-info/SOURCES.txt
ConsistentHashing.egg-info/dependency_links.txt
ConsistentHashing.egg-info/top_level.txt