Metadata-Version: 1.0
Name: ConsistentHashing
Version: 0.1.9
Summary: A simple implement of consistent hashing.
Home-page: UNKNOWN
Author: Ziang Guo
Author-email: iziang@yeah.net
License: BSD
Keywords: hashing hash consistent distributed
Platform: Any
Classifier: Development Status :: 5 - Production/Stable
Classifier: Intended Audience :: Developers
Classifier: License :: OSI Approved :: BSD License
Classifier: Operating System :: OS Independent
Classifier: Programming Language :: Python
Classifier: Topic :: Software Development :: Libraries :: Python Modules
